cooperbench/__about__.py
cooperbench/__init__.py
cooperbench/cli.py
cooperbench/py.typed
cooperbench/utils.py
cooperbench/agents/README.md
cooperbench/agents/__init__.py
cooperbench/agents/registry.py
cooperbench/agents/mini_swe_agent/__init__.py
cooperbench/agents/mini_swe_agent/adapter.py
cooperbench/agents/mini_swe_agent/agents/__init__.py
cooperbench/agents/mini_swe_agent/agents/default.py
cooperbench/agents/mini_swe_agent/config/__init__.py
cooperbench/agents/mini_swe_agent/config/mini.yaml
cooperbench/agents/mini_swe_agent/connectors/__init__.py
cooperbench/agents/mini_swe_agent/connectors/git.py
cooperbench/agents/mini_swe_agent/connectors/messaging.py
cooperbench/agents/mini_swe_agent/environments/__init__.py
cooperbench/agents/mini_swe_agent/environments/modal.py
cooperbench/agents/mini_swe_agent/models/__init__.py
cooperbench/agents/mini_swe_agent/models/litellm_model.py
cooperbench/agents/mini_swe_agent/models/utils/__init__.py
cooperbench/agents/mini_swe_agent/models/utils/cache_control.py
cooperbench/agents/mini_swe_agent/utils/__init__.py
cooperbench/agents/mini_swe_agent/utils/log.py
cooperbench/agents/swe_agent/LICENSE
cooperbench/agents/swe_agent/__init__.py
cooperbench/agents/swe_agent/adapter.py
cooperbench/agents/swe_agent/exceptions.py
cooperbench/agents/swe_agent/types.py
cooperbench/agents/swe_agent/agent/__init__.py
cooperbench/agents/swe_agent/agent/action_sampler.py
cooperbench/agents/swe_agent/agent/agents.py
cooperbench/agents/swe_agent/agent/history_processors.py
cooperbench/agents/swe_agent/agent/models.py
cooperbench/agents/swe_agent/agent/problem_statement.py
cooperbench/agents/swe_agent/agent/reviewer.py
cooperbench/agents/swe_agent/agent/hooks/__init__.py
cooperbench/agents/swe_agent/agent/hooks/abstract.py
cooperbench/agents/swe_agent/config/coop.yaml
cooperbench/agents/swe_agent/config/default.yaml
cooperbench/agents/swe_agent/connectors/__init__.py
cooperbench/agents/swe_agent/connectors/git.py
cooperbench-0.0.2.dist-info/METADATA
cooperbench-0.0.2.dist-info/WHEEL
cooperbench-0.0.2.dist-info/entry_points.txt
cooperbench-0.0.2.dist-info/RECORD
