Metadata-Version: 2.4
Name: cooperbench
Version: 0.0.2
Summary: Multi-agent coordination benchmark for collaborative code generation
Project-URL: Homepage, https://cooperbench.com
Project-URL: Documentation, https://cooperbench.com
Project-URL: Repository, https://github.com/cooperbench/CooperBench
Project-URL: Issues, https://github.com/cooperbench/CooperBench/issues
Project-URL: Dataset, https://huggingface.co/datasets/CodeConflict/cooperbench-dataset
Project-URL: Paper, https://arxiv.org/abs/2601.13295
Author: Arpandeep Khatua, Hao Zhu, Peter Tran, Arya Prabhudesai, Frederic Sadrieh, Johann K. Lieberwirth, Xinkai Yu, Yicheng Fu, Michael J. Ryan, Jiaxin Pei, Diyi Yang
License: MIT
Keywords: ai-agents,benchmark,code-generation,collaboration,coordination,llm,multi-agent,software-engineering
Classifier: Development Status :: 4 - Beta
Classifier: Intended Audience :: Developers
Classifier: Intended Audience :: Science/Research
Classifier: License :: OSI Approved :: MIT License
Classifier: Operating System :: OS Independent
Classifier: Programming Language :: Python :: 3
Classifier: Programming Language :: Python :: 3.12
Classifier: Programming Language :: Python :: 3.13
Classifier: Topic :: Scientific/Engineering :: Artificial Intelligence
Classifier: Topic :: Software Development :: Testing
Classifier: Typing :: Typed
Requires-Python: >=3.12
Requires-Dist: jinja2>=3.0
Requires-Dist: litellm>=1.0
Requires-Dist: modal>=0.70
Requires-Dist: platformdirs>=3.0
Requires-Dist: pydantic>=2.0
Requires-Dist: python-dotenv>=1.0
Requires-Dist: pyyaml>=6.0
Requires-Dist: redis>=7.0
Requires-Dist: rich>=13.0
Requires-Dist: tenacity>=8.0
Provides-Extra: all
Requires-Dist: mypy>=1.10; extra == 'all'
Requires-Dist: pytest-asyncio>=0.23; extra == 'all'
Requires-Dist: pytest-cov>=4.0; extra == 'all'
Requires-Dist: pytest>=8.0; extra == 'all'
Requires-Dist: ruff>=0.4; extra == 'all'
Requires-Dist: swe-agent>=1.0; extra == 'all'
Provides-Extra: dev
Requires-Dist: mypy>=1.10; extra == 'dev'
Requires-Dist: pytest-asyncio>=0.23; extra == 'dev'
Requires-Dist: pytest-cov>=4.0; extra == 'dev'
Requires-Dist: pytest>=8.0; extra == 'dev'
Requires-Dist: ruff>=0.4; extra == 'dev'
Provides-Extra: swe-agent
Requires-Dist: swe-agent>=1.0; extra == 'swe-agent'
